parallellib/__init__.py
parallellib/parallel_mpi.py
parallellib/parallel_multiprocessing.py
parallellib-2025.7.22.dist-info/METADATA
parallellib-2025.7.22.dist-info/WHEEL
parallellib-2025.7.22.dist-info/licenses/LICENSE
parallellib-2025.7.22.dist-info/RECORD
